passivapi/__about__.py
passivapi/__init__.py
passivapi/passivapi.py
passivapi-0.0.5.dist-info/METADATA
passivapi-0.0.5.dist-info/WHEEL
passivapi-0.0.5.dist-info/licenses/LICENSE.txt
passivapi-0.0.5.dist-info/RECORD
