Metadata-Version: 2.1
Name: passivapi
Version: 0.0.5
Summary: API wrapper for the Passiv API
Project-URL: Documentation, https://github.com/GarethDJohn/python-passivapi#readme
Project-URL: Issues, https://github.com/GarethDJohn/python-passivapi/issues
Project-URL: Source, https://github.com/GarethDJohn/python-passivapi
Author-email: Gareth John <gdjohn@logicalparadox.co.uk>
License-File: LICENSE.txt
Classifier: Development Status :: 4 - Beta
Classifier: Programming Language :: Python
Classifier: Programming Language :: Python :: 3.7
Classifier: Programming Language :: Python :: 3.8
Classifier: Programming Language :: Python :: 3.9
Classifier: Programming Language :: Python :: 3.10
Classifier: Programming Language :: Python :: 3.11
Classifier: Programming Language :: Python :: Implementation :: CPython
Classifier: Programming Language :: Python :: Implementation :: PyPy
Requires-Python: >=3.7
Requires-Dist: requests>=2.28.1
